ax_devil_device_api/__init__.py
ax_devil_device_api/client.py
ax_devil_device_api/core/__init__.py
ax_devil_device_api/core/auth.py
ax_devil_device_api/core/config.py
ax_devil_device_api/core/endpoints.py
ax_devil_device_api/core/transport_client.py
ax_devil_device_api/examples/__init__.py
ax_devil_device_api/examples/analytics_metadata_cli.py
ax_devil_device_api/examples/analytics_mqtt_cli.py
ax_devil_device_api/examples/api_discovery_cli.py
ax_devil_device_api/examples/cli_core.py
ax_devil_device_api/examples/device_debug_cli.py
ax_devil_device_api/examples/device_info_cli.py
ax_devil_device_api/examples/feature_flags_cli.py
ax_devil_device_api/examples/geocoordinates_cli.py
ax_devil_device_api/examples/main_cli.py
ax_devil_device_api/examples/media_cli.py
ax_devil_device_api/examples/mqtt_client_cli.py
ax_devil_device_api/examples/network_cli.py
ax_devil_device_api/examples/ssh_cli.py
ax_devil_device_api/features/__init__.py
ax_devil_device_api/features/analytics_metadata.py
ax_devil_device_api/features/analytics_mqtt.py
ax_devil_device_api/features/api_discovery.py
ax_devil_device_api/features/base.py
ax_devil_device_api/features/device_debug.py
ax_devil_device_api/features/device_info.py
ax_devil_device_api/features/feature_flags.py
ax_devil_device_api/features/geocoordinates.py
ax_devil_device_api/features/media.py
ax_devil_device_api/features/mqtt_client.py
ax_devil_device_api/features/network.py
ax_devil_device_api/features/ssh.py
ax_devil_device_api/utils/__init__.py
ax_devil_device_api/utils/errors.py
ax_devil_device_api-0.5.0.dist-info/licenses/LICENSE
ax_devil_device_api-0.5.0.dist-info/METADATA
ax_devil_device_api-0.5.0.dist-info/WHEEL
ax_devil_device_api-0.5.0.dist-info/entry_points.txt
ax_devil_device_api-0.5.0.dist-info/top_level.txt
ax_devil_device_api-0.5.0.dist-info/RECORD
