Metadata-Version: 2.4
Name: ax-devil-device-api
Version: 0.5.0
Summary: Python library for interacting with Axis device APIs
Author-email: Rasmus Rynell <Rynell.Rasmus@gmail.com>
License: MIT
Project-URL: Homepage, https://github.com/rasmusrynell/ax-devil-device-api
Project-URL: Repository, https://github.com/rasmusrynell/ax-devil-device-api.git
Project-URL: Documentation, https://github.com/rasmusrynell/ax-devil-device-api#readme
Project-URL: Bug Tracker, https://github.com/rasmusrynell/ax-devil-device-api/issues
Requires-Python: >=3.10
License-File: LICENSE
Requires-Dist: requests>=2.25.0
Requires-Dist: click>=8.0.0
Requires-Dist: rich>=13.9.4
Requires-Dist: urllib3>=2.5.0
Dynamic: license-file
